flask_mico/__init__.py
flask_mico/api_view.py
flask_mico/app.py
flask_mico/cli.py
flask_mico/conf.py
flask_mico/constant.py
flask_mico/field_validator.py
flask_mico/log.py
flask_mico/urls.py
flask_mico/util.py
flask_mico/error/__init__.py
flask_mico/error/err_handle.py
flask_mico/error/errors.py
flask_mico/middleware/__init__.py
flask_mico/middleware/mid_handle.py
flask_mico/middleware/translate.py
flask_mico-0.1.1.dist-info/LICENSE
flask_mico-0.1.1.dist-info/METADATA
flask_mico-0.1.1.dist-info/WHEEL
flask_mico-0.1.1.dist-info/entry_points.txt
flask_mico-0.1.1.dist-info/top_level.txt
flask_mico-0.1.1.dist-info/RECORD
