Metadata-Version: 2.1
Name: flask-mico
Version: 0.1.1
Summary: flask mico
Home-page: https://github.com/YE-Kits/flask_mico
Author: @buzz
License: UNKNOWN
Platform: all
Classifier: Programming Language :: Python :: 3
Requires-Dist: flask
Requires-Dist: cerberus
